[
    {
        "name": "桃子",
        "content" : "桃花可以观赏，果实多汁，可以生食，核仁可以使用。",
        "imageName": "",
        "EnglishName": "Peach",
        "PinYin":"táo zi"
    },
    {
        "name": "苹果",
        "content" : "苹果果实圆形，是人们常食的水果之一。",
        "imageName": "",
        "EnglishName": "Apple",
        "PinYin":"píng guǒ"
    },
    {
        "name": "香蕉",
        "content" : "香蕉果实长形，稍弯，味香甜。",
        "imageName": "",
        "EnglishName": "Banana",
        "PinYin":"xiāng jiāo"
    },
    {
        "name": "梨子",
        "content" : "梨树的果实，通常用来食用，不仅味美多汁，甜中带酸。",
        "imageName": "",
        "EnglishName": "Pear",
        "PinYin":"lí"
    },
    {
        "name": "西瓜",
        "content" : "西瓜为夏季的水果，果肉微甜，能降温去暑。",
        "imageName": "",
        "EnglishName": "Watermelon",
        "PinYin":"xī guā"
    },
    {
        "name": "橘子",
        "content" : "橘子是橘树的果实，多汁可食用的，是人们常食的水果之一。",
        "imageName": "",
        "EnglishName": "Orange",
        "PinYin":"jú zi"
    },
    {
        "name": "草莓",
        "content" : "红色的果实，多汁可食",
        "imageName": "",
        "EnglishName": "Strawberry",
        "PinYin":"cǎo méi"
    },
    {
        "name": "桑果",
        "content" : "桑果是桑树的成熟果实，味甜汁多。",
        "imageName": "",
        "EnglishName": "Mulberry",
        "PinYin":"sāng shèn"
    },
    {
        "name": "杨桃",
        "content" : "杨桃的果实，由绿色至黄色。通常略有酸味。",
        "imageName": "",
        "EnglishName": "Carambola",
        "PinYin":"yáng táo"
    },
    {
        "name": "哈密瓜",
        "content" : "产于新疆的一类优良甜瓜品种，味甜，果实大。",
        "imageName": "",
        "EnglishName": "Hami melon",
        "PinYin":"hā mì guā"
    },
    {
        "name": "芒果",
        "content" : "芒果为著名热带水果之一，含有糖、蛋白质、粗纤维等。",
        "imageName": "",
        "EnglishName": "Mango",
        "PinYin":"máng guǒ"
    },
    {
        "name": "菠萝",
        "content" : "菠萝是热带水果之一，原产巴西，亚马逊河流域。",
        "imageName": "",
        "EnglishName": "Pineapple",
        "PinYin":"bō luó"
    },
    {
        "name": "石榴",
        "content" : "石榴果实营养丰富，维生素C含量高。",
        "imageName": "",
        "EnglishName": "Pomegranate",
        "PinYin":"shí liu"
    },
    {
        "name": "猕猴桃",
        "content" : "也称奇异果，因猕猴喜欢吃，所以叫猕猴桃。",
        "imageName": "",
        "EnglishName": "Kiwi fruit",
        "PinYin":"mí hóu táo"
    },
    {
        "name": "荔枝",
        "content" : "荔枝果实熟时紫红色，是我国特产，多吃易上火。",
        "imageName": "",
        "EnglishName": "Litchi",
        "PinYin":"lì zhī"
    },
    {
        "name": "木瓜",
        "content" : "木瓜果实长椭圆形，味酸涩，可入药。",
        "imageName": "",
        "EnglishName": "Pawpaw",
        "PinYin":"mù ɡuā"
    },
    {
        "name": "葡萄",
        "content" : "葡萄，成串，味酸甜，多汁，可生食、制干、酿酒。",
        "imageName": "",
        "EnglishName": "Grape",
        "PinYin":"pú tao"
    },
    {
        "name": "龙眼",
        "content" : "龙眼又叫做桂圆，常与荔枝相提并论。",
        "imageName": "",
        "EnglishName": "Litchi",
        "PinYin":"lóng yǎn"
    },
    {
        "name": "香瓜",
        "content" : "香瓜又称甜瓜，是营养丰富，风味鲜美的水果。",
        "imageName": "",
        "EnglishName": "Casaba",
        "PinYin":"xiāng guā"
    },
    {
        "name": "火龙果",
        "content" : "火龙果营养丰富，功能独特，属于良性水果，味甜，多汁。",
        "imageName": "",
        "EnglishName": "Pitaya",
        "PinYin":"huǒ lónɡ ɡuǒ"
    },
    {
        "name": "榴莲",
        "content" : "榴莲的气味浓烈，营养丰富，被誉为“水果之王”。",
        "imageName": "",
        "EnglishName": "Durian",
        "PinYin":"liú lián"
    },
    {
        "name": "甘蔗",
        "content" : "甘蔗有扁平的2列叶，多节的杆，含糖，可以食用。",
        "imageName": "",
        "EnglishName": "Sugarcane",
        "PinYin":"gān zhe"
    },
    {
        "name": "核桃",
        "content" : "核桃，对人体有益。是深受老百姓喜欢的坚果类食品之一。",
        "imageName": "",
        "EnglishName": "Walnut",
        "PinYin":"hé tao"
    }
    
]
